Metadata-Version: 1.2
Name: configa
Version: 1.1.0
Summary: Python config wrapper, with added goodness
Home-page: https://github.com/loum/configa
Author: Lou Markovski
Author-email: lou.markovski@gmail.com
Maintainer: Lou Markovski
Maintainer-email: lou.markovski@gmail.com
License: MIT
Platform: UNKNOWN
Classifier: Development Status :: 4 - Beta
Classifier: Framework :: Pytest
Classifier: Intended Audience :: Developers
Classifier: Topic :: Software Development :: Testing
Classifier: Programming Language :: Python
Classifier: Programming Language :: Python :: 3
Classifier: Programming Language :: Python :: 3.6
Classifier: Programming Language :: Python :: 3.7
Classifier: Programming Language :: Python :: Implementation :: CPython
Classifier: Programming Language :: Python :: Implementation :: PyPy
Classifier: Operating System :: OS Independent
Classifier: License :: OSI Approved :: MIT License
Requires-Python: >=3.6
